aiodl/__init__.py
aiodl/__main__.py
aiodl/aiodl.py
aiodl/utils.py
aiodl/version.py
aiodl-0.4.6.dist-info/DESCRIPTION.rst
aiodl-0.4.6.dist-info/METADATA
aiodl-0.4.6.dist-info/RECORD
aiodl-0.4.6.dist-info/WHEEL
aiodl-0.4.6.dist-info/entry_points.txt
aiodl-0.4.6.dist-info/metadata.json
aiodl-0.4.6.dist-info/top_level.txt
