Metadata-Version: 2.0
Name: aiodl
Version: 0.4.6
Summary: Aiodl -- Yet another command line download accelerator.
Home-page: https://github.com/cshuaimin/aiodl
Author: cshuaimin
Author-email: chen_shuaimin@outlook.com
License: MIT
Keywords: asynchronous download
Platform: UNKNOWN
Classifier: Development Status :: 3 - Alpha
Classifier: License :: OSI Approved :: MIT License
Classifier: Programming Language :: Python :: 3.5
Classifier: Programming Language :: Python :: 3.6
Requires-Python: >=3.5
Requires-Dist: aiohttp
Requires-Dist: tqdm
Requires-Dist: termcolor
Requires-Dist: argparse
Requires-Dist: fake-useragent
